ebi/__init__.py
ebi/ols/__init__.py
ebi/ols/api/__init__.py
ebi/ols/api/base.py
ebi/ols/api/client.py
ebi/ols/api/exceptions.py
ebi/ols/api/helpers.py
ebi_ols_client-1.1.0.dist-info/LICENSE
ebi_ols_client-1.1.0.dist-info/METADATA
ebi_ols_client-1.1.0.dist-info/NOTICE
ebi_ols_client-1.1.0.dist-info/WHEEL
ebi_ols_client-1.1.0.dist-info/top_level.txt
ebi_ols_client-1.1.0.dist-info/RECORD
