Metadata-Version: 2.1
Name: ebi-ols-client
Version: 1.1.0
Summary: OLS - REST Api Client - python library
Home-page: https://github.com/Ensembl/ols-client
Author: Marc Chakiachvili
Author-email: mchakiachvili@ebi.ac.uk
License: Apache 2.0
Platform: UNKNOWN
Classifier: Development Status :: 4 - Beta
Classifier: Environment :: Console
Classifier: Intended Audience :: Science/Research
Classifier: License :: OSI Approved :: Apache Software License
Classifier: Natural Language :: English
Classifier: Programming Language :: Python :: 3.6
Classifier: Topic :: Scientific/Engineering :: Bio-Informatics
Classifier: Topic :: Software Development :: Libraries :: Python Modules
Requires-Dist: inflection (==0.3.1)
Requires-Dist: coreapi (==2.3.3)
Requires-Dist: hal-codec (==1.0.2)
Requires-Dist: requests (==2.22.0)
